pymdownx_blocks/__init__.py
pymdownx_blocks/dirtree.py
pymdownx_blocks-0.1.1.dist-info/METADATA
pymdownx_blocks-0.1.1.dist-info/WHEEL
pymdownx_blocks-0.1.1.dist-info/licenses/LICENSE
pymdownx_blocks-0.1.1.dist-info/RECORD
