Metadata-Version: 2.1
Name: pymdownx-blocks
Version: 0.1.1
Summary: A Collection of Blocks for PyMdownX
Author-email: Tyler Baur <baur.tyler@gmail.com>
License-File: LICENSE
Classifier: Intended Audience :: Developers
Classifier: License :: OSI Approved :: MIT License
Classifier: Operating System :: OS Independent
Classifier: Programming Language :: Python
Classifier: Programming Language :: Python :: 3 :: Only
Classifier: Programming Language :: Python :: 3.8
Classifier: Programming Language :: Python :: 3.9
Classifier: Programming Language :: Python :: 3.10
Classifier: Programming Language :: Python :: 3.11
Classifier: Programming Language :: Python :: 3.12
Requires-Python: >=3.8
Requires-Dist: pymdown-extensions>=10.3.1
Requires-Dist: pyyaml>=6.0.1
